scorepyo/__init__.py
scorepyo/_utils.py
scorepyo/binarizers.py
scorepyo/calibration.py
scorepyo/exceptions.py
scorepyo/models.py
scorepyo/ranking.py
scorepyo-0.2.3.dist-info/LICENSE
scorepyo-0.2.3.dist-info/METADATA
scorepyo-0.2.3.dist-info/WHEEL
scorepyo-0.2.3.dist-info/top_level.txt
scorepyo-0.2.3.dist-info/RECORD
