Metadata-Version: 2.1
Name: scorepyo
Version: 0.2.3
Summary: This is the scorepyo repository.
Home-page: https://github.com/drskd/scorepyo
Author: S. Kaddani
License: MIT
Keywords: scorepyo risk score
Classifier: Programming Language :: Python :: 3
Classifier: Programming Language :: Python :: 3.8
Classifier: Programming Language :: Python :: 3.9
Requires-Python: >=3.8
License-File: LICENSE
Requires-Dist: numpy (==1.23.5)
Requires-Dist: pandas (==1.5.2)
Requires-Dist: pandera (==0.13.4)
Requires-Dist: scikit-learn (==1.1.3)
Requires-Dist: interpret (==0.3.0)
Requires-Dist: optuna (==3.0.3)
Requires-Dist: botorch (==0.7.3)
Requires-Dist: tabulate (==0.9.0)
Requires-Dist: cvxpy (==1.3.0)
Requires-Dist: dask[distributed] (==2023.1.1)
Requires-Dist: bokeh (<3,>=2.4.2)
Requires-Dist: fasterrisk (==0.1.2)
Requires-Dist: mrmr-selection (==0.2.8)
Provides-Extra: dev
Requires-Dist: black[jupyter] (==22.3.0) ; extra == 'dev'
Requires-Dist: isort (==5.10.1) ; extra == 'dev'
Requires-Dist: pytest (==7.1.2) ; extra == 'dev'
Requires-Dist: pytest-cov (==3.0.0) ; extra == 'dev'
Requires-Dist: pylint (==2.13.8) ; extra == 'dev'
Requires-Dist: mypy (==1.0.0) ; extra == 'dev'
Requires-Dist: bandit[toml] (==1.7.4) ; extra == 'dev'
Requires-Dist: pip-tools ; extra == 'dev'
Requires-Dist: types-python-slugify (==6.1.0) ; extra == 'dev'
Requires-Dist: dash (==2.7.0) ; extra == 'dev'
Requires-Dist: build ; extra == 'dev'
Requires-Dist: twine ; extra == 'dev'
Provides-Extra: doc
Requires-Dist: ipython ; extra == 'doc'
Requires-Dist: jupyter-book (==0.13.1) ; extra == 'doc'
Requires-Dist: sphinx-autoapi ; extra == 'doc'
Requires-Dist: ghp-import ; extra == 'doc'
Requires-Dist: myst-nb ; extra == 'doc'
Requires-Dist: myst-parser ; extra == 'doc'
Provides-Extra: ipy
Requires-Dist: ipython ; extra == 'ipy'
Requires-Dist: ipykernel ; extra == 'ipy'
Requires-Dist: ipython-genutils ; extra == 'ipy'
Requires-Dist: notebook ; extra == 'ipy'
Requires-Dist: jupyterlab ; extra == 'ipy'
